learning_paths/__init__.py
learning_paths/admin.py
learning_paths/apps.py
learning_paths/compat.py
learning_paths/conftest.py
learning_paths/keys.py
learning_paths/models.py
learning_paths/receivers.py
learning_paths/settings.py
learning_paths/urls.py
learning_paths/api/__init__.py
learning_paths/api/urls.py
learning_paths/api/v1/__init__.py
learning_paths/api/v1/filters.py
learning_paths/api/v1/permissions.py
learning_paths/api/v1/serializers.py
learning_paths/api/v1/urls.py
learning_paths/api/v1/utils.py
learning_paths/api/v1/views.py
learning_paths/migrations/0001_initial.py
learning_paths/migrations/0002_learningpath_uuid.py
learning_paths/migrations/0003_learningpath_subtitle.py
learning_paths/migrations/0004_auto_20240207_1633.py
learning_paths/migrations/0005_learningpathstep_weight_learningpathgradingcriteria.py
learning_paths/migrations/0006_enrollment_models.py
learning_paths/migrations/0007_replace_uuid_with_learningpathkey.py
learning_paths/migrations/0008_remove_learningpathstep_relative_due_date_in_days.py
learning_paths/migrations/0009_remove_learningpath_slug.py
learning_paths/migrations/0010_learningpath_invite_only.py
learning_paths/migrations/0011_replace_learningpath_image_url_with_image.py
learning_paths/migrations/0012_alter_learningpath_subtitle.py
learning_paths/migrations/0013_enrollment_audit.py
learning_paths/migrations/0014_remove_learningpath_duration_in_days_and_more.py
learning_paths/migrations/0015_make_skill_level_optional.py
learning_paths/migrations/__init__.py
learning_paths/templates/learning_paths/base.html
learning_paths_plugin-0.3.5.dist-info/licenses/LICENSE.txt
learning_paths_plugin-0.3.5.dist-info/METADATA
learning_paths_plugin-0.3.5.dist-info/WHEEL
learning_paths_plugin-0.3.5.dist-info/entry_points.txt
learning_paths_plugin-0.3.5.dist-info/top_level.txt
learning_paths_plugin-0.3.5.dist-info/RECORD
