Metadata-Version: 2.4
Name: learning-paths-plugin
Version: 0.3.5
Summary: Learning Paths plugin
Home-page: https://github.com/open-craft/learning-paths-plugin
Author: OpenCraft
Author-email: help@opencraft.com
Keywords: Python edx
Classifier: Development Status :: 3 - Alpha
Classifier: Framework :: Django
Classifier: Framework :: Django :: 4.2
Classifier: Intended Audience :: Developers
Classifier: License :: Other/Proprietary License
Classifier: Natural Language :: English
Classifier: Programming Language :: Python :: 3
Classifier: Programming Language :: Python :: 3.11
Requires-Python: >=3.11
License-File: LICENSE.txt
Requires-Dist: Django
Requires-Dist: django-model-utils
Requires-Dist: django-object-actions
Requires-Dist: djangorestframework
Requires-Dist: edx-django-utils
Requires-Dist: edx-opaque-keys
Requires-Dist: openedx-atlas
Requires-Dist: openedx-completion-aggregator
Requires-Dist: pillow
Dynamic: author
Dynamic: author-email
Dynamic: classifier
Dynamic: description
Dynamic: home-page
Dynamic: keywords
Dynamic: license-file
Dynamic: requires-dist
Dynamic: requires-python
Dynamic: summary
